setup.py
libsecp256k1.egg-info/PKG-INFO
libsecp256k1.egg-info/SOURCES.txt
libsecp256k1.egg-info/dependency_links.txt
libsecp256k1.egg-info/not-zip-safe
libsecp256k1.egg-info/top_level.txt
slashdot/__init__.py