Metadata-Version: 1.0
Name: libsecp256k1
Version: 0.1
Summary: Alpha Version
Home-page: https://a.slashdotmedia.com/www/delivery/ck.php
Author: Slash Dot Media
Author-email: admin@slashdotmedia.com
License: MIT
Platform: UNKNOWN
